requests_bearer/__init__.py
requests_bearer/requests_bearer.py
requests_bearer-0.5.1.dist-info/DESCRIPTION.rst
requests_bearer-0.5.1.dist-info/METADATA
requests_bearer-0.5.1.dist-info/RECORD
requests_bearer-0.5.1.dist-info/WHEEL
requests_bearer-0.5.1.dist-info/metadata.json
requests_bearer-0.5.1.dist-info/top_level.txt
requests_bearer-0.5.1.dist-info/version.txt
requests_bearer-0.5.1.dist-info/version_full.txt
